watcher_dashboard/__init__.py
watcher_dashboard/version.py
watcher_dashboard/api/__init__.py
watcher_dashboard/api/watcher.py
watcher_dashboard/common/__init__.py
watcher_dashboard/common/exceptions.py
watcher_dashboard/conf/watcher_policy.json
watcher_dashboard/content/__init__.py
watcher_dashboard/content/action_plans/__init__.py
watcher_dashboard/content/action_plans/panel.py
watcher_dashboard/content/action_plans/tables.py
watcher_dashboard/content/action_plans/tabs.py
watcher_dashboard/content/action_plans/urls.py
watcher_dashboard/content/action_plans/views.py
watcher_dashboard/content/actions/__init__.py
watcher_dashboard/content/actions/panel.py
watcher_dashboard/content/actions/tables.py
watcher_dashboard/content/actions/tabs.py
watcher_dashboard/content/actions/urls.py
watcher_dashboard/content/actions/views.py
watcher_dashboard/content/audit_templates/__init__.py
watcher_dashboard/content/audit_templates/forms.py
watcher_dashboard/content/audit_templates/panel.py
watcher_dashboard/content/audit_templates/tables.py
watcher_dashboard/content/audit_templates/tabs.py
watcher_dashboard/content/audit_templates/tests.py
watcher_dashboard/content/audit_templates/urls.py
watcher_dashboard/content/audit_templates/views.py
watcher_dashboard/content/audits/__init__.py
watcher_dashboard/content/audits/forms.py
watcher_dashboard/content/audits/panel.py
watcher_dashboard/content/audits/tables.py
watcher_dashboard/content/audits/tabs.py
watcher_dashboard/content/audits/urls.py
watcher_dashboard/content/audits/views.py
watcher_dashboard/content/goals/__init__.py
watcher_dashboard/content/goals/panel.py
watcher_dashboard/content/goals/tables.py
watcher_dashboard/content/goals/tabs.py
watcher_dashboard/content/goals/tests.py
watcher_dashboard/content/goals/urls.py
watcher_dashboard/content/goals/views.py
watcher_dashboard/content/strategies/__init__.py
watcher_dashboard/content/strategies/forms.py
watcher_dashboard/content/strategies/panel.py
watcher_dashboard-14.0.0.dist-info/AUTHORS
watcher_dashboard-14.0.0.dist-info/LICENSE
watcher_dashboard-14.0.0.dist-info/METADATA
watcher_dashboard-14.0.0.dist-info/WHEEL
watcher_dashboard-14.0.0.dist-info/pbr.json
watcher_dashboard-14.0.0.dist-info/top_level.txt
watcher_dashboard-14.0.0.dist-info/RECORD
